pesticide/__init__.py
pesticide-0.0.1.dist-info/METADATA
pesticide-0.0.1.dist-info/WHEEL
pesticide-0.0.1.dist-info/top_level.txt
pesticide-0.0.1.dist-info/RECORD
