Metadata-Version: 2.1
Name: pesticide
Version: 0.0.1
Summary: Inspect your models and get rid of bugs in your Arboretum.
Home-page: https://github.com/helveg/pesticide
Author: Robin De Schepper
Author-email: robingilbert.deschepper@unipv.it
License: MIT
Platform: UNKNOWN
Classifier: Programming Language :: Python :: 3
Classifier: Programming Language :: Python :: 3.8
Classifier: Programming Language :: Python :: 3.9
Classifier: Operating System :: OS Independent
Requires-Python: >=3.8
Requires-Dist: plotly
Requires-Dist: arborize (>=2.0.1)
Provides-Extra: dev
Requires-Dist: sphinx ; extra == 'dev'
Requires-Dist: pre-commit ; extra == 'dev'
Requires-Dist: black (>=20.8b1) ; extra == 'dev'
Requires-Dist: sphinxcontrib-contentui ; extra == 'dev'
